.eslintrc
.gitignore
LICENSE
MANIFEST.in
README.rst
manage.py
requires.txt
settings.py
setup.py
template.wsgi
testflat.folia.xml
FoLiA_Linguistic_Annotation_Tool.egg-info/PKG-INFO
FoLiA_Linguistic_Annotation_Tool.egg-info/SOURCES.txt
FoLiA_Linguistic_Annotation_Tool.egg-info/dependency_links.txt
FoLiA_Linguistic_Annotation_Tool.egg-info/not-zip-safe
FoLiA_Linguistic_Annotation_Tool.egg-info/requires.txt
FoLiA_Linguistic_Annotation_Tool.egg-info/top_level.txt
docs/Annotation_guidelines_2014.tex
docs/Makefile
docs/administration_guide.rst
docs/conf.py
docs/confidenceslider.png
docs/createlinkreference.png
docs/edit1.png
docs/edit2.png
docs/editdeletion.png
docs/editdialog.png
docs/editforms.png
docs/editinsertion.png
docs/editinternalrelation.png
docs/editmerge.png
docs/featureediting.png
docs/flat_clst_demo_pres.pdf
docs/flat_clst_demo_pres.tex
docs/globalannotations.png
docs/globalannotations2.png
docs/higherorderbutton.png
docs/higherordercomment.png
docs/highlight1.png
docs/highlight2.png
docs/history.png
docs/hover.png
docs/index.rst
docs/installation_guide.rst
docs/lama-logo-transparent.png
docs/login.png
docs/login_configuration.png
docs/logo.png
docs/menu_modes.png
docs/morphtree.png
docs/mydocuments.png
docs/ner.png
docs/newannotation.png
docs/newdeclaration.png
docs/perspectivemenu.png
docs/poster.png
docs/poster.svg
docs/poster2.png
docs/poster2.svg
docs/queuedsubmission.png
docs/righttoleft.png
docs/search.png
docs/searchcql.png
docs/sentenceperspective.png
docs/spanselect.png
docs/syntree.png
docs/user_guide.rst
flat/__init__.py
flat/comm.py
flat/converters.py
flat/urls.py
flat/views.py
flat/wsgi.py
flat/modes/__init__.py
flat/modes/editor/__init__.py
flat/modes/editor/urls.py
flat/modes/editor/views.py
flat/modes/editor/templates/editor.html
flat/modes/metadata/__init__.py
flat/modes/metadata/models.py
flat/modes/metadata/urls.py
flat/modes/metadata/views.py
flat/modes/metadata/templates/metadata.html
flat/modes/structureeditor/__init__.py
flat/modes/structureeditor/urls.py
flat/modes/structureeditor/views.py
flat/modes/structureeditor/templates/structureeditor.html
flat/modes/viewer/__init__.py
flat/modes/viewer/urls.py
flat/modes/viewer/views.py
flat/modes/viewer/templates/search.html
flat/modes/viewer/templates/treeview.html
flat/modes/viewer/templates/viewer.html
