Metadata-Version: 2.1
Name: FoLiA-Linguistic-Annotation-Tool
Version: 0.11.4
Summary: FLAT is a web-based linguistic annotation environment based around the FoLiA format (https://proycon.github.io/folia), a rich XML-based format for linguistic annotation. Flat allows users to view annotated FoLiA documents and enrich these documents with new annotations, a wide variety of linguistic annotation types is supported through the FoLiA paradigm.
Home-page: https://github.com/proycon/flat
Author: Maarten van Gompel
Author-email: proycon@anaproy.nl
License: GPL
Keywords: linguistics,annotation,nlp,computational linguistics,folia
Classifier: Development Status :: 5 - Production/Stable
Classifier: Topic :: Text Processing :: Linguistic
Classifier: Programming Language :: Python :: 3.7
Classifier: Programming Language :: Python :: 3.8
Classifier: Programming Language :: Python :: 3.9
Classifier: Programming Language :: Python :: 3.10
Classifier: Programming Language :: Python :: 3.11
Classifier: Operating System :: POSIX
Classifier: Intended Audience :: Developers
Classifier: Intended Audience :: Science/Research
Classifier: License :: OSI Approved :: GNU General Public License v3 (GPLv3)
Requires-Python: >=3.7
License-File: LICENSE
Requires-Dist: folia>=2.5.7
Requires-Dist: Django>=3.0
Requires-Dist: requests
Requires-Dist: foliadocserve>=0.7.8
Requires-Dist: mozilla-django-oidc
